iuv.py
iuv-0.1.1.dist-info/METADATA
iuv-0.1.1.dist-info/WHEEL
iuv-0.1.1.dist-info/entry_points.txt
iuv-0.1.1.dist-info/licenses/LICENSE
iuv-0.1.1.dist-info/RECORD
