Metadata-Version: 2.4
Name: iuv
Version: 0.1.1
Summary: Reruns uv foo/bar.py if files in foo/../... change.
Author-email: Fabian Guera <fabian.guera@gmail.com>
License-File: LICENSE
Requires-Python: >=3.8
Requires-Dist: watchfiles>=0.21
